NET/_Win.py
NET/__init__.py
NET/_calc.py
NET/_log.py
NET-2.4.dist-info/METADATA
NET-2.4.dist-info/WHEEL
NET-2.4.dist-info/top_level.txt
NET-2.4.dist-info/RECORD
