Metadata-Version: 2.1
Name: NET
Version: 2.4
Summary: A Powerfull Networking Package For Servers/LocalHosts ETC
Author: Hunter Mikesell & Ben
Author-email: huntermikesell84@gmail.com
License: MIT
Classifier: Programming Language :: Python :: 3
Classifier: License :: OSI Approved :: MIT License
Classifier: Operating System :: OS Independent
